procgen_tools/__init__.py
procgen_tools/episodes.py
procgen_tools/graph_mazes.py
procgen_tools/maze.py
procgen_tools/metrics.py
procgen_tools/models.py
procgen_tools/procgen_wrappers.py
procgen_tools/vfield.py
procgen_tools-0.1.dist-info/METADATA
procgen_tools-0.1.dist-info/WHEEL
procgen_tools-0.1.dist-info/top_level.txt
procgen_tools-0.1.dist-info/RECORD
