Metadata-Version: 2.1
Name: procgen-tools
Version: 0.1
Summary: Tools for working with Procgen environments
Requires-Dist: gym (==0.21.0)
Requires-Dist: gym3 (==0.3.3)
Requires-Dist: torch (==1.13.1)
Requires-Dist: numpy (==1.24.1)
Requires-Dist: matplotlib (==3.6.3)
Requires-Dist: tqdm (==4.64.1)
Requires-Dist: ipywidgets (==7.*)
Requires-Dist: procgen (==0.10.7)
